dlprog/__init__.py
dlprog/progress.py
dlprog/utils.py
dlprog-1.2.8.dist-info/LICENSE
dlprog-1.2.8.dist-info/METADATA
dlprog-1.2.8.dist-info/WHEEL
dlprog-1.2.8.dist-info/top_level.txt
dlprog-1.2.8.dist-info/RECORD
