Metadata-Version: 2.1
Name: dlprog
Version: 1.2.8
Summary: A progress bar that aggregates the values of each iteration.
Home-page: https://github.com/misya11p/dlprog
Author: misya11p
License: MIT
Project-URL: Repository, https://github.com/misya11p/dlprog
Keywords: iterator progress bar aggregate deep-learning machine-learning
Classifier: Development Status :: 5 - Production/Stable
Classifier: Programming Language :: Python
Classifier: Programming Language :: Python :: 3
Classifier: Programming Language :: Python :: 3 :: Only
Classifier: License :: OSI Approved :: MIT License
Requires-Python: >=3
License-File: LICENSE
